credipronto/kafka/__init__.py
credipronto/observability/__init__.py
credipronto/observability/apm.py
credipronto/observability/logger.py
credipronto/sqs/__init__.py
credipronto-0.2.3.dist-info/METADATA
credipronto-0.2.3.dist-info/WHEEL
credipronto-0.2.3.dist-info/top_level.txt
credipronto-0.2.3.dist-info/RECORD
