Metadata-Version: 2.4
Name: credipronto
Version: 0.2.3
Summary: Biblioteca de utilidades time de dados
Author-email: Alexandre Vieira <avsilva@credipronto.com.br>
License: MIT
Requires-Dist: elastic-apm>=6.24.0
Requires-Dist: dotenv>=0.9.9
